django_zero/__init__.py
django_zero/__main__.py
django_zero/_version.py
django_zero/assets.py
django_zero/errors.py
django_zero/jinja2.py
django_zero/package.json
django_zero/urls.py
django_zero/utils.py
django_zero/views.py
django_zero/yarn.lock
django_zero/auth/__init__.py
django_zero/auth/decorators.py
django_zero/auth/forms.py
django_zero/commands/__init__.py
django_zero/commands/base.py
django_zero/commands/create.py
django_zero/commands/delegates.py
django_zero/commands/lifecycle.py
django_zero/commands/templates/__init__.py
django_zero/commands/templates/app/cookiecutter.json
django_zero/commands/templates/app/{{cookiecutter.name}}/__init__.py
django_zero/commands/templates/app/{{cookiecutter.name}}/admin.py
django_zero/commands/templates/app/{{cookiecutter.name}}/apps.py
django_zero/commands/templates/app/{{cookiecutter.name}}/models.py
django_zero/commands/templates/app/{{cookiecutter.name}}/urls.py
django_zero/commands/templates/app/{{cookiecutter.name}}/views.py
django_zero/commands/templates/app/{{cookiecutter.name}}/jinja2/{{cookiecutter.name}}/default.html
django_zero/commands/templates/app/{{cookiecutter.name}}/migrations/__init__.py
django_zero/commands/templates/app/{{cookiecutter.name}}/resources/assets/{{cookiecutter.name}}.js
django_zero/commands/templates/app/{{cookiecutter.name}}/resources/assets/{{cookiecutter.name}}.scss
django_zero/commands/templates/config/celery/app/tasks.py
django_zero/commands/templates/config/celery/project/config/celery.py
django_zero/commands/templates/config/channels/project/config/asgi.py
django_zero/commands/templates/config/channels/project/config/routing.py
django_zero/commands/templates/project/cookiecutter.json
django_zero/commands/templates/project/{{cookiecutter.name}}/.gitignore
django_zero/commands/templates/project/{{cookiecutter.name}}/MANIFEST.in
django_zero/commands/templates/project/{{cookiecutter.name}}/Makefile
django_zero/commands/templates/project/{{cookiecutter.name}}/Projectfile
django_zero-0.1.0.dist-info/METADATA
django_zero-0.1.0.dist-info/WHEEL
django_zero-0.1.0.dist-info/entry_points.txt
django_zero-0.1.0.dist-info/top_level.txt
django_zero-0.1.0.dist-info/RECORD
