Metadata-Version: 2.1
Name: django-zero
Version: 0.1.0
Summary: Zero-configuration django projects.
Home-page: https://github.com/hartym/django-zero
Author: Romain Dorgueil
Author-email: romain@dorgueil.net
License: Apache License, Version 2.0
Download-URL: https://github.com/hartym/django-zero/archive/0.1.0.tar.gz
Platform: UNKNOWN
Requires-Dist: brotli (~=1.0.9)
Requires-Dist: django (<3.2,~=3.1)
Requires-Dist: django-allauth (~=0.43.0)
Requires-Dist: django-includes (~=0.3.1)
Requires-Dist: jinja2 (~=2.11)
Requires-Dist: mondrian (~=0.8)
Requires-Dist: whitenoise (~=5.2.0)
Provides-Extra: celery
Requires-Dist: celery (~=4.0) ; extra == 'celery'
Requires-Dist: django-celery-beat (~=2.1.0) ; extra == 'celery'
Requires-Dist: django-celery-results (~=1.2.1) ; extra == 'celery'
Provides-Extra: channels
Requires-Dist: channels (~=3.0.0) ; extra == 'channels'
Requires-Dist: daphne (~=3.0.0) ; extra == 'channels'
Provides-Extra: dev
Requires-Dist: cookiecutter (~=1.7) ; extra == 'dev'
Requires-Dist: coverage (~=5.3) ; extra == 'dev'
Requires-Dist: django-extensions (~=3.0.9) ; extra == 'dev'
Requires-Dist: django-debug-toolbar (~=3.1.1) ; extra == 'dev'
Requires-Dist: honcho (~=1.0) ; extra == 'dev'
Requires-Dist: isort ; extra == 'dev'
Requires-Dist: medikit (~=0.7) ; extra == 'dev'
Requires-Dist: pyquery (~=1.4) ; extra == 'dev'
Requires-Dist: pytest (>=5.4.0) ; extra == 'dev'
Requires-Dist: pytest-cov (~=2.7) ; extra == 'dev'
Requires-Dist: pytest-django (~=4.0) ; extra == 'dev'
Requires-Dist: werkzeug (~=1.0) ; extra == 'dev'
Provides-Extra: prod
Requires-Dist: gunicorn (~=20.0) ; extra == 'prod'
